{
  "mallId": "goods.mallId",
  "mallName": "mall.mallData.mallName",
  "reviewNum": "reviewStore.mallReview.reviewNum",
  "reviewNumStr": "reviewStore.mallReview.reviewNumStr",
  "mallLogo": "mall.mallData.mallLogo",
  "goodsNum": "mall.mallData.goodsNum",
  "goodsNumV2": "mall.mallData.goodsNumV2",
  "goodsNumUnit": "mall.mallData.goodsNumUnit",
  "goodsNumLowercaseUnit": "mall.mallData.goodsNumUnit[1]",
  "mallStar": "review.reviewData.mallReview.mallScore",
  "mallStarStr": "reviewStore.mallReview.mallScoreText",
  "shortenMallStar": "mall.mallData.shortenMallStar",
  "goodsSalesNum": "mall.mallData.goodsSalesNumUnit[0]",
  "goodsSalesNumUnit": "mall.mallData.goodsSalesNumUnit",
  "goodsSalesBrief": "mall.mallData.goodsSalesNumUnit[1]",
  "followerNum": "mall.mallData.followerNumUnit[0]",
  "followerNumUnit": "mall.mallData.followerNumUnit",
  "semiManaged": "goods.isLocalGoods",
  "channelType": "mall.mallData.channelType",
  "searchUrl": "mall.mallData.searchUrl",
  "seoUrl": "mall.mallData.seoUrl",
  "mallJumpUrl": "mall.mallData.mallJumpUrl",
  "shareInfo": "mall.mallData.shareInfo",
  "scoreNumInfoList": "mall.mallData.scoreNumInfoList[0]",
  "topShopInfo": "mall.mallData.topShopInfo",
  "mallReviewLabelShow": "mall.mallData.mallReviewLabelShow",
  "mallReviewLinkUrl": "reviewStore.mallReview.mallReviewLinkUrl",
  "optList": "crumbOptList",
  "mallTags": "mall.mallData.mallTags[0]",
  "source": "webLayoutData.headerData.titleBarList",
  "semiManagedMallTags": "mall.mallData.semiManagedMallTags",
  "isExpire": "mall.mallData.isExpire",
  "userAgent": "userAgent",
  "fromUrl": "webLayoutData.commonData.query.refer_page_name",
  "serverTime": "serverTime",
  "timezone": "localInfo.timezone",
  "siteId": "webLayoutData.headerData.region.regionInfo.siteId",
  "lang": "lang",
  "selectedLang": "webLayoutData.headerData.region.regionInfo.selectedLang"
}